neon_phal_plugin_reset/__init__.py
neon_phal_plugin_reset/config.py
neon_phal_plugin_reset/create_media.py
neon_phal_plugin_reset/version.py
tests/__init__.py
tests/test_plugin.py
neon_phal_plugin_reset-0.5.0.dist-info/LICENSE.md
neon_phal_plugin_reset-0.5.0.dist-info/METADATA
neon_phal_plugin_reset-0.5.0.dist-info/WHEEL
neon_phal_plugin_reset-0.5.0.dist-info/entry_points.txt
neon_phal_plugin_reset-0.5.0.dist-info/top_level.txt
neon_phal_plugin_reset-0.5.0.dist-info/RECORD
