Metadata-Version: 2.1
Name: neon-phal-plugin-reset
Version: 0.5.0
Summary: Device Reset Interface
Home-page: https://github.com/NeonGeckoCom/neon-phal-plugin-reset
Author: Neongecko
Author-email: developers@neon.ai
License: BSD-3
License-File: LICENSE.md
Requires-Dist: ovos-utils>=0.0.26,~=0.0
Requires-Dist: ovos-plugin-manager>=0.0.20,~=0.0
Requires-Dist: requests
Requires-Dist: ovos-bus-client>=0.0.3,~=0.0
Requires-Dist: ovos-skill-installer~=0.0.5
Requires-Dist: psutil
Requires-Dist: neon-utils~=1.0
Provides-Extra: test
Requires-Dist: pytest; extra == "test"
